[
  {
    "Start Time": "2025-05-22T15:25:18.667490",
    "End Time": "2025-05-22T15:25:38.829617",
    "License Plate": []
  },
  {
    "Start Time": "2025-05-22T15:28:11.043562",
    "End Time": "2025-05-22T15:28:21.082708",
    "License Plate": []
  },
  {
    "Start Time": "2025-05-22T15:28:21.082708",
    "End Time": "2025-05-22T15:28:31.244166",
    "License Plate": []
  },
  {
    "Start Time": "2025-05-22T15:28:31.244166",
    "End Time": "2025-05-22T15:28:41.357718",
    "License Plate": []
  },
  {
    "Start Time": "2025-05-22T15:31:43.219244",
    "End Time": "2025-05-22T15:31:53.294765",
    "License Plate": [
      "LS15EBC",
      "LSI5EBC"
    ]
  },
  {
    "Start Time": "2025-05-22T15:31:53.294765",
    "End Time": "2025-05-22T15:32:03.380480",
    "License Plate": [
      "LS15EBC",
      "LS5EBC",
      "LSI5EBC"
    ]
  },
  {
    "Start Time": "2025-05-22T15:32:03.380480",
    "End Time": "2025-05-22T15:32:13.644780",
    "License Plate": [
      "LS15EBC",
      "LSI5EBC"
    ]
  }
]